belql/cli.py
belql/run.py
belql/static/belquery.js
belql/static/gif/loading.gif
belql/templates/index.html
belql/templates/layout.html
belql/templates/macros.html
belql/utils.py
belql-0.3.0.dist-info/LICENSE
belql-0.3.0.dist-info/METADATA
belql-0.3.0.dist-info/WHEEL
belql-0.3.0.dist-info/entry_points.txt
belql-0.3.0.dist-info/RECORD
