Metadata-Version: 2.1
Name: belql
Version: 0.3.0
Summary: BEL query language Python package.
Home-page: https://github.com/e-bel/belql
License: Apache Software License 2.0
Keywords: Knowledge Graphs,Systems Biology,BEL
Author: Bruce Schultz
Author-email: bschultz013@gmail.com
Requires-Python: >=3.10,<4.0
Classifier: Development Status :: 4 - Beta
Classifier: Intended Audience :: Developers
Classifier: License :: OSI Approved :: Apache Software License
Classifier: License :: Other/Proprietary License
Classifier: Operating System :: OS Independent
Classifier: Programming Language :: Python :: 3
Classifier: Programming Language :: Python :: 3.10
Classifier: Programming Language :: Python :: 3.11
Classifier: Topic :: Software Development :: Libraries :: Python Modules
Requires-Dist: Flask (>=2.3.2,<3.0.0)
Requires-Dist: click (>=8.1.6,<9.0.0)
Requires-Dist: ebel-rest (>=1.0.24,<2.0.0)
Requires-Dist: requests (>=2.31.0,<3.0.0)
Requires-Dist: waitress (>=2.1.2,<3.0.0)
Project-URL: Repository, https://github.com/e-bel/belql
